pyramid_objective/__init__.py
pyramid_objective-0.0.2.dist-info/DESCRIPTION.rst
pyramid_objective-0.0.2.dist-info/METADATA
pyramid_objective-0.0.2.dist-info/RECORD
pyramid_objective-0.0.2.dist-info/WHEEL
pyramid_objective-0.0.2.dist-info/metadata.json
pyramid_objective-0.0.2.dist-info/namespace_packages.txt
pyramid_objective-0.0.2.dist-info/pbr.json
pyramid_objective-0.0.2.dist-info/top_level.txt
